nonebot_plugin_aidraw/__init__.py
nonebot_plugin_aidraw/config.py
nonebot_plugin_aidraw/count.py
nonebot_plugin_aidraw/database.py
nonebot_plugin_aidraw/draw.py
nonebot_plugin_aidraw/limit.py
nonebot_plugin_aidraw/manage.py
nonebot_plugin_aidraw-0.7.1.dist-info/WHEEL
nonebot_plugin_aidraw-0.7.1.dist-info/METADATA
nonebot_plugin_aidraw-0.7.1.dist-info/licenses/LICENSE
nonebot_plugin_aidraw-0.7.1.dist-info/RECORD
